Linux101HacksZhongwenban/README.md
Linux101HacksZhongwenban/__init__.py
Linux101HacksZhongwenban/__main__.py
Linux101HacksZhongwenban/file.epub
Linux101HacksZhongwenban/index.html
Linux101HacksZhongwenban/css/__init__.py
Linux101HacksZhongwenban/css/annotations.css
Linux101HacksZhongwenban/css/main.css
Linux101HacksZhongwenban/css/normalize.css
Linux101HacksZhongwenban/css/popup.css
Linux101HacksZhongwenban/font/__init__.py
Linux101HacksZhongwenban/font/fontello.eot
Linux101HacksZhongwenban/font/fontello.svg
Linux101HacksZhongwenban/font/fontello.ttf
Linux101HacksZhongwenban/font/fontello.woff
Linux101HacksZhongwenban/img/__init__.py
Linux101HacksZhongwenban/img/annotator-glyph-sprite.png
Linux101HacksZhongwenban/img/annotator-icon-sprite.png
Linux101HacksZhongwenban/img/apple-touch-icon.png
Linux101HacksZhongwenban/img/cancelfullscreen.png
Linux101HacksZhongwenban/img/close.png
Linux101HacksZhongwenban/img/fullscreen.png
Linux101HacksZhongwenban/img/loader.gif
Linux101HacksZhongwenban/img/menu-icon.png
Linux101HacksZhongwenban/img/save.png
Linux101HacksZhongwenban/img/saved.png
Linux101HacksZhongwenban/img/settings-s.png
Linux101HacksZhongwenban/img/settings.png
Linux101HacksZhongwenban/img/star.png
Linux101HacksZhongwenban/js/__init__.py
Linux101HacksZhongwenban/js/epub.js
Linux101HacksZhongwenban/js/epub.min.js
Linux101HacksZhongwenban/js/epub.min.map
Linux101HacksZhongwenban/js/hooks.min.js
Linux101HacksZhongwenban/js/hooks.min.map
Linux101HacksZhongwenban/js/reader.js
Linux101HacksZhongwenban/js/reader.js.map
Linux101HacksZhongwenban/js/reader.min.js
Linux101HacksZhongwenban/js/reader.min.map
Linux101HacksZhongwenban/js/hooks/__init__.py
Linux101HacksZhongwenban/js/hooks/extensions/__init__.py
Linux101HacksZhongwenban/js/hooks/extensions/highlight.js
Linux101HacksZhongwenban/js/libs/__init__.py
Linux101HacksZhongwenban/js/libs/jquery.min.js
Linux101HacksZhongwenban/js/libs/localforage.min.js
Linux101HacksZhongwenban/js/libs/screenfull.js
linux_101_hacks_zhongwenban-2024.3.2.0.dist-info/METADATA
linux_101_hacks_zhongwenban-2024.3.2.0.dist-info/WHEEL
linux_101_hacks_zhongwenban-2024.3.2.0.dist-info/entry_points.txt
linux_101_hacks_zhongwenban-2024.3.2.0.dist-info/top_level.txt
linux_101_hacks_zhongwenban-2024.3.2.0.dist-info/RECORD
